{
  "서울특별시 성북구 화랑로18길 6 (상월곡동)": {
    "lat": 37.6065724,
    "lng": 127.0502215
  },
  "서울특별시 서초구 강남대로30길": {
    "lat": 37.4829879,
    "lng": 127.0397643
  },
  "서울특별시 강서구 화곡동 산 41-16": {
    "lat": null,
    "lng": null
  },
  "서울특별시 중랑구 겸재로9길 45 (면목동)": {
    "lat": 37.5876616,
    "lng": 127.0782842
  },
  "서울특별시 강남구 삼성로 66 번지": {
    "lat": null,
    "lng": null
  },
  "서울특별시 강북구 삼양로92길 40 (수유동)": {
    "lat": 37.6369787,
    "lng": 127.018327
  },
  "서울특별시 서대문구 증가로20길 43 (북가좌동)": {
    "lat": 37.5813976,
    "lng": 126.9187542
  },
  "서울특별시 양천구 목동로3길 106 (신정동)": {
    "lat": 37.5114654,
    "lng": 126.8623322
  },
  "서울특별시 서대문구 홍제천로2길 111 (연희동)": {
    "lat": 37.5717889,
    "lng": 126.9236565
  },
  "서울특별시 은평구 연서로 415 (진관동)": {
    "lat": 37.6320399,
    "lng": 126.9301667
  },
  "서울특별시 도봉구 도봉로169가길 52 (도봉동)": {
    "lat": 37.6803788,
    "lng": 127.0440384
  },
  "서울특별시 은평구 연서로3나길 11-30 (역촌동)": {
    "lat": 37.6030866,
    "lng": 126.9130651
  },
  "서울특별시 은평구 통일로89길 12-6 (갈현동)": {
    "lat": 37.6250308,
    "lng": 126.9187494
  },
  "서울특별시 중구 다산로6길 11 (신당동)": {
    "lat": 37.5521443,
    "lng": 127.0095219
  },
  "서울특별시 송파구 백제고분로32길 41 (삼전동)": {
    "lat": 37.500856,
    "lng": 127.0950103
  },
  "서울특별시 동작구 상도로11길 7 (대방동)": {
    "lat": 37.5006112,
    "lng": 126.9296492
  },
  "서울특별시 성북구 한천로 708 (장위동)": {
    "lat": 37.6200853,
    "lng": 127.0535146
  },
  "서울특별시 중랑구 동일로138길 28 (중화동)": {
    "lat": 37.6032007,
    "lng": 127.0800163
  },
  "서울특별시 성북구 종암로15길 10 (종암동)": {
    "lat": 37.5976657,
    "lng": 127.0340058
  },
  "서울특별시 노원구 노원로16길 15 (하계동, 시립노원노인종합복지관)": {
    "lat": 37.6428963,
    "lng": 127.0735534
  },
  "서울특별시 용산구 독서당로11길 16 (한남동)": {
    "lat": 37.5315466,
    "lng": 127.006786
  },
  "서울특별시 강서구 화곡로61길 85 (등촌동)": {
    "lat": 37.5581184,
    "lng": 126.8474584
  },
  "서울특별시 관악구 보라매로 35 (봉천동)": {
    "lat": 37.4946712,
    "lng": 126.9273149
  },
  "서울특별시 종로구 삼일대로 467 (경운동)": {
    "lat": 37.5759673,
    "lng": 126.9858531
  },
  "서울특별시 서대문구 독립문로8길 57 (천연동)": {
    "lat": 37.5673091,
    "lng": 126.9589549
  },
  "서울특별시 도봉구 덕릉로60차길 8 (창동)": {
    "lat": 37.6369113,
    "lng": 127.0418878
  },
  "서울특별시 중랑구 신내로15길 175 (신내동)": {
    "lat": 37.6134104,
    "lng": 127.0911909
  },
  "서울특별시 도봉구 우이천로 363 (쌍문동)": {
    "lat": 37.6372865,
    "lng": 127.0374112
  },
  "서울특별시 동대문구 제기로33길 25 (청량리동)": {
    "lat": 37.5872415,
    "lng": 127.0498534
  },
  "서울특별시 도봉구 시루봉로15라길 59-9 (방학동)": {
    "lat": 37.6699187,
    "lng": 127.0329926
  },
  "서울특별시 종로구 율곡로19길 17-8 (이화동)": {
    "lat": 37.5769678,
    "lng": 127.0060251
  },
  "서울특별시 성동구 마조로 77 (마장동)": {
    "lat": 37.564214,
    "lng": 127.0414102
  },
  "서울특별시 영등포구 도림로 482 (문래동3가)": {
    "lat": 37.5139683,
    "lng": 126.8956121
  },
  "서울특별시 용산구 청파로83길 26 (서계동)": {
    "lat": 37.5520746,
    "lng": 126.9679945
  },
  "서울특별시 강남구 도곡로27길 27 (역삼동)": {
    "lat": 37.4932492,
    "lng": 127.0422819
  },
  "서울특별시 서초구 서초대로54길": {
    "lat": 37.4930629,
    "lng": 127.0161649
  },
  "서울특별시 강동구 천중로17길 42-16 (천호동)": {
    "lat": 37.5465794,
    "lng": 127.1309949
  },
  "서울특별시 은평구 증산로15길 47 (신사동)": {
    "lat": 37.5907947,
    "lng": 126.9076845
  },
  "서울특별시 도봉구 도당로2길 12-13 (쌍문동)": {
    "lat": 37.6585952,
    "lng": 127.0360892
  },
  "서울특별시 강동구 양재대로156길 28 (고덕동)": {
    "lat": 37.556318,
    "lng": 127.148621
  },
  "서울특별시 마포구 환일길 3 (아현동)": {
    "lat": 37.554686,
    "lng": 126.9608795
  },
  "서울특별시 금천구 시흥대로51길 93-32 (시흥동)": {
    "lat": 37.4505533,
    "lng": 126.9011955
  },
  "서울특별시 마포구 서강로 68 (창전동)": {
    "lat": 37.5467851,
    "lng": 126.9290455
  },
  "서울특별시 광진구 군자로 88 (군자동)": {
    "lat": 37.5539702,
    "lng": 127.0739447
  },
  "서울특별시 강남구 역삼로69길 22 (대치동)": {
    "lat": 37.5029659,
    "lng": 127.0539847
  },
  "서울특별시 강남구 봉은사로 332 (역삼동)": {
    "lat": 37.505496,
    "lng": 127.0280541
  },
  "서울특별시 금천구 독산로72길 86-5 (독산동)": {
    "lat": 37.4684422,
    "lng": 126.9044717
  },
  "서울특별시 마포구 신촌로26길 10 (노고산동)": {
    "lat": 37.5553747,
    "lng": 126.9426453
  },
  "서울특별시 송파구 송파동 113번지 2호   4,5,6층": {
    "lat": null,
    "lng": null
  },
  "서울특별시 구로구 부일로9길 111 (온수동)": {
    "lat": 37.4945087,
    "lng": 126.8265958
  },
  "서울특별시 노원구 공릉로 129 (공릉동)": {
    "lat": 37.6282791,
    "lng": 127.077498
  },
  "서울특별시 강서구 화곡동 890번지": {
    "lat": null,
    "lng": null
  },
  "서울특별시 구로구 새말로16길 25 번지 7 호": {
    "lat": null,
    "lng": null
  },
  "서울특별시 성동구 마장로 141 (상왕십리동, 왕십리도선동 복합청사 노인복지센터)": {
    "lat": 37.5679098,
    "lng": 127.0255527
  },
  "서울특별시 강동구 동남로71길 32-5 (명일동)": {
    "lat": 37.5523206,
    "lng": 127.1541935
  },
  "서울특별시 송파구 충민로 184 (장지동)": {
    "lat": 37.4782288,
    "lng": 127.1223034
  },
  "서울특별시 은평구 응암로21가길 5-1 (응암동)": {
    "lat": 37.5949973,
    "lng": 126.9169615
  },
  "서울특별시 강남구 강남대로128길 59 (논현동)": {
    "lat": 37.5119121,
    "lng": 127.0262175
  },
  "서울특별시 은평구 연서로32길 17-11 (불광동)": {
    "lat": 37.620186,
    "lng": 126.9247578
  },
  "서울특별시 강서구 월정로30길 963층~5층": {
    "lat": null,
    "lng": null
  },
  "서울특별시 강서구 화곡로58길 30-7": {
    "lat": 37.5525285,
    "lng": 126.8543442
  },
  "서울특별시 중구 동호로20길 24 (신당동)": {
    "lat": 37.5598501,
    "lng": 127.0097473
  },
  "서울특별시 용산구 새창로12길 11-8 (도원동)": {
    "lat": 37.5375277,
    "lng": 126.9534825
  },
  "서울특별시 용산구 후암로34길 21-8 (후암동)": {
    "lat": 37.5513989,
    "lng": 126.9784817
  },
  "서울특별시 용산구 효창원로15길 37 (산천동)": {
    "lat": 37.5363042,
    "lng": 126.9533528
  },
  "서울특별시 용산구 원효로64길 21 (원효로2가)": {
    "lat": 37.5357846,
    "lng": 126.9641902
  },
  "서울특별시 용산구 한강대로53길 8 (한강로1가)": {
    "lat": 37.5337182,
    "lng": 126.9713432
  },
  "서울특별시 용산구 이촌로 80-8 (이촌동)": {
    "lat": 37.5249455,
    "lng": 126.9568709
  },
  "서울특별시 성동구 무학로6길 9 (홍익동)": {
    "lat": 37.5654903,
    "lng": 127.0311557
  },
  "서울특별시 성동구 금호로 172-1 (금호동1가)": {
    "lat": 37.5502462,
    "lng": 127.0259504
  },
  "서울특별시 성동구 금호동3가 165-1": {
    "lat": 37.54998,
    "lng": 127.02213
  },
  "서울특별시 광진구 광나루로44길 47 (구의동)": {
    "lat": 37.5413829,
    "lng": 127.090956
  },
  "서울특별시 동대문구 사가정로 98 (전농동)": {
    "lat": 37.5781737,
    "lng": 127.0629586
  },
  "서울특별시 중랑구 상봉로25길 27 (상봉동)": {
    "lat": 37.5947167,
    "lng": 127.0915048
  },
  "서울특별시 은평구 통일로 786 (불광동)": {
    "lat": 37.6095555,
    "lng": 126.9284369
  },
  "서울특별시 은평구 은평로16길 11 (응암동)": {
    "lat": 37.5992403,
    "lng": 126.9296513
  },
  "서울특별시 은평구 가좌로 200 (응암동)": {
    "lat": 37.5973018,
    "lng": 126.9072501
  },
  "서울특별시 은평구 갈현로35길 12-13 (갈현동)": {
    "lat": 37.621468,
    "lng": 126.9159543
  },
  "서울특별시 은평구 통일로 951 (갈현동)": {
    "lat": 37.6050498,
    "lng": 126.9347481
  },
  "서울특별시 서대문구 신촌로 293 (북아현동)": {
    "lat": 37.5575485,
    "lng": 126.9593811
  },
  "서울특별시 서대문구 연희로 64-14 (연희동)": {
    "lat": 37.5635593,
    "lng": 126.9296188
  },
  "서울특별시 서대문구 연희로10길 17-6 (연희동)": {
    "lat": 37.5656687,
    "lng": 126.9314131
  },
  "서울특별시 서대문구 북아현로4나길 17 (북아현동)": {
    "lat": 37.5589027,
    "lng": 126.9575814
  },
  "서울특별시 마포구 성산동 572-200": {
    "lat": null,
    "lng": null
  },
  "서울특별시 마포구 마포대로14길 15-1 (공덕동)": {
    "lat": 37.5486439,
    "lng": 126.9564252
  },
  "서울특별시 양천구 목동중앙북로8길 41 (목동)": {
    "lat": 37.5450703,
    "lng": 126.8681451
  },
  "서울특별시 양천구 목동동로 353 (목동)": {
    "lat": 37.526657,
    "lng": 126.8748737
  },
  "서울특별시 양천구 오목로 270 (목동)": {
    "lat": 37.5261241,
    "lng": 126.8645174
  },
  "서울특별시 양천구 목동중앙북로8길 49 (목동)": {
    "lat": 37.546142,
    "lng": 126.8685966
  },
  "서울특별시 양천구 목동서로 271 (신정동)": {
    "lat": 37.5382636,
    "lng": 126.8831734
  },
  "서울특별시 양천구 신월로 188 (신월동,3층)": {
    "lat": 37.5223633,
    "lng": 126.8641229
  },
  "서울특별시 강서구 까치산로2길 89-1 (화곡동)": {
    "lat": 37.5391891,
    "lng": 126.8430918
  },
  "서울특별시 강서구 강서로15길 132 (화곡동)": {
    "lat": 37.5321238,
    "lng": 126.8420645
  },
  "서울특별시 강서구 개화동로23길 111 (방화동)": {
    "lat": 37.5662148,
    "lng": 126.8087683
  },
  "서울특별시 금천구 탑골로2길 56 (시흥동)": {
    "lat": 37.4504206,
    "lng": 126.9132458
  },
  "서울특별시 동작구 상도로 259 (상도동)": {
    "lat": 37.504073,
    "lng": 126.9474701
  },
  "서울특별시 관악구 봉천동 13-44": {
    "lat": 37.484665,
    "lng": 126.9484961
  },
  "서울특별시 서초구 방배로5길 43 (방배동)": {
    "lat": 37.4780309,
    "lng": 126.9987209
  },
  "서울특별시 서초구 논현로5길 28 (양재동)": {
    "lat": 37.4727265,
    "lng": 127.0491227
  },
  "서울특별시 강남구 언주로85길 23-11 (역삼동, 역삼성당)": {
    "lat": 37.500661,
    "lng": 127.0417953
  },
  "서울특별시 강동구 양재대로 1342, 2층 (둔촌동, 강동숨;터)": {
    "lat": null,
    "lng": null
  },
  "서울특별시 서초구 명달로 52 (서초동)": {
    "lat": 37.4784336,
    "lng": 127.0059992
  },
  "서울특별시 서초구 서초대로54길 45 (서초동)": {
    "lat": 37.4923281,
    "lng": 127.0168833
  },
  "서울특별시 서초구 서초대로34가길 43 (방배동)": {
    "lat": 37.4872172,
    "lng": 126.9982233
  },
  "서울특별시 관악구 난곡로26길 43 (신림동)": {
    "lat": 37.4695615,
    "lng": 126.9241392
  },
  "서울특별시 서대문구 통일로9길 11 (냉천동, 서대문성당)": {
    "lat": 37.5669826,
    "lng": 126.9644292
  },
  "서울특별시 강서구 방화동로 52 (방화동)": {
    "lat": 37.5632988,
    "lng": 126.8101329
  },
  "서울특별시 은평구 역말로8길 25 (대조동)": {
    "lat": 37.6092836,
    "lng": 126.9228676
  },
  "서울특별시 용산구 서빙고로 39 (한강로3가)": {
    "lat": 37.5231501,
    "lng": 127.0010764
  },
  "서울특별시 용산구 이태원로15길 1, 3층 (이태원동)": {
    "lat": null,
    "lng": null
  },
  "서울특별시 양천구 목동 909번지 2호 평광교회": {
    "lat": null,
    "lng": null
  },
  "서울특별시 은평구 가좌로10길 10 (응암동, 서문교회)": {
    "lat": 37.5915868,
    "lng": 126.9167567
  },
  "서울특별시 은평구 구산동 16번지 26호": {
    "lat": null,
    "lng": null
  },
  "충청남도 태안군 안면읍 중신로 343": {
    "lat": null,
    "lng": null
  },
  "서울특별시 금천구 독산동 1088번지 1호": {
    "lat": null,
    "lng": null
  },
  "서울특별시 은평구 응암로20길 23 (응암동)": {
    "lat": 37.5927603,
    "lng": 126.9195829
  },
  "서울특별시 은평구 역말로 14 (역촌동)": {
    "lat": 37.6059554,
    "lng": 126.9167771
  },
  "서울특별시 종로구 김상옥로 37 (연지동)": {
    "lat": 37.5733614,
    "lng": 126.9970971
  },
  "서울특별시 영등포구 도림로 304 (신길동)": {
    "lat": 37.5139683,
    "lng": 126.8956121
  },
  "서울특별시 종로구 충신길 22 (종로6가)": {
    "lat": 37.5739983,
    "lng": 127.0082578
  },
  "서울특별시 영등포구 문래로20길 52": {
    "lat": 37.5170277,
    "lng": 126.8926289
  },
  "서울특별시 용산구 이촌로 188 (이촌동)": {
    "lat": 37.5215479,
    "lng": 126.9660936
  },
  "서울특별시 영등포구 대림동 899번지 2호 영등포보건분소 2층": {
    "lat": null,
    "lng": null
  },
  "서울특별시 강서구 화곡로53길 21 (화곡동)": {
    "lat": 37.551419,
    "lng": 126.847687
  },
  "서울특별시 강서구 공항대로55길 61 (등촌동, 등촌1동천주교회)": {
    "lat": 37.5544192,
    "lng": 126.8613194
  },
  "서울특별시 송파구 백제고분로42길 5 (송파동)": {
    "lat": 37.5058895,
    "lng": 127.1098693
  },
  "서울특별시 강서구 강서로45다길 12-27 (화곡동, 발산동성당)": {
    "lat": 37.5471608,
    "lng": 126.8334834
  },
  "서울특별시 영등포구 신길로40길 10 (신길동)": {
    "lat": 37.5068348,
    "lng": 126.9120725
  },
  "서울특별시 강서구 금낭화로 52 (방화동)": {
    "lat": 37.5685495,
    "lng": 126.8111555
  },
  "서울특별시 양천구 신월로24길 8 (신월동)": {
    "lat": 37.519694,
    "lng": 126.8460587
  },
  "서울특별시 관악구 신림로29길 8 (신림동, 신림현대아파트 경로당)": {
    "lat": 37.4750266,
    "lng": 126.932013
  },
  "서울특별시 중랑구 봉우재로65길 13 (망우동)": {
    "lat": 37.5956938,
    "lng": 127.0970907
  },
  "서울특별시 중랑구 양원역로 89 (망우동)": {
    "lat": 37.6083225,
    "lng": 127.1053744
  },
  "서울특별시 강서구 양천로47가길 25-10 (가양동, 양천교회)": {
    "lat": 37.5707333,
    "lng": 126.8391204
  },
  "서울특별시 강남구 헌릉로637길 12 (세곡동, 강남제일교회)": {
    "lat": 37.4668386,
    "lng": 127.1093647
  },
  "서울특별시 성북구 솔샘로 8 (정릉동)": {
    "lat": 37.6080368,
    "lng": 127.0047429
  },
  "서울특별시 은평구 응암로 376, 5층 (녹번동)": {
    "lat": null,
    "lng": null
  },
  "서울특별시 중랑구 동일로134길 3 (중화동)": {
    "lat": 37.6009475,
    "lng": 127.080518
  },
  "서울특별시 강서구 강서로56가길 166, 203동 지하1~2층 (등촌동)": {
    "lat": null,
    "lng": null
  },
  "서울특별시 강남구 도곡로 540 (대치동)": {
    "lat": 37.5002839,
    "lng": 127.0666519
  },
  "서울특별시 강남구 밤고개로21길 50 (율현동, 천주교 세곡동성당)": {
    "lat": 37.4734787,
    "lng": 127.1126986
  },
  "서울특별시 강동구 아리수로93가길 34 (강일동)": {
    "lat": 37.5753204,
    "lng": 127.1696087
  },
  "서울특별시 중랑구 용마산로 432 (면목동)": {
    "lat": 37.571,
    "lng": 127.08626
  },
  "서울특별시 광진구 뚝섬로56길 20 (자양동)": {
    "lat": 37.5295663,
    "lng": 127.0826859
  },
  "서울특별시 중랑구 면목로27나길 32 (면목동)": {
    "lat": 37.5751495,
    "lng": 127.0827771
  },
  "서울특별시 중랑구 면목로92길 34 (상봉동)": {
    "lat": 37.5954266,
    "lng": 127.087954
  },
  "서울특별시 중랑구 용마산로112나길 7 (망우동)": {
    "lat": 37.5960691,
    "lng": 127.1017894
  },
  "서울특별시 노원구 수락산로 214 (상계동)": {
    "lat": 37.6635644,
    "lng": 127.0754393
  },
  "서울특별시 강남구 논현로132길 18 (논현동, 서울영동교회)": {
    "lat": 37.5153131,
    "lng": 127.0324585
  },
  "서울특별시 마포구 독막로 189 (신수동)": {
    "lat": 37.5428706,
    "lng": 126.9487736
  },
  "서울특별시 은평구 통일로 767, B117호 (대조동, 베르디움 STAY1)": {
    "lat": null,
    "lng": null
  },
  "서울특별시 도봉구 도당로13길 22, 3층 (방학동)": {
    "lat": null,
    "lng": null
  },
  "서울특별시 관악구 관악로5길 95, 1층 (봉천동)": {
    "lat": null,
    "lng": null
  },
  "서울특별시 성동구 송정18가길 9, 2층 (송정동)": {
    "lat": null,
    "lng": null
  },
  "서울특별시 노원구 동일로 1456, 711동동 1207호 (상계동, 상계주공아파트)": {
    "lat": null,
    "lng": null
  },
  "서울특별시 중랑구 숙선옹주로 69 (묵동)": {
    "lat": 37.6180617,
    "lng": 127.0865145
  },
  "서울특별시 중랑구 면목로35길 21 (면목동)": {
    "lat": 37.5788718,
    "lng": 127.0844663
  },
  "서울특별시 양천구 등촌로 208, 2층 (목동)": {
    "lat": null,
    "lng": null
  },
  "서울특별시 강남구 학동로47길 30 (논현동)": {
    "lat": 37.5176828,
    "lng": 127.0385917
  },
  "서울특별시 강북구 오현로 208 (번동, 번동주공3단지아파트 309동 주민복지관-2)": {
    "lat": 37.6300883,
    "lng": 127.0414241
  },
  "서울특별시 동작구 매봉로 36 (상도1동)": {
    "lat": 37.5056176,
    "lng": 126.9502653
  },
  "서울특별시 강남구 논현로6길 6 (개포동)": {
    "lat": 37.4729032,
    "lng": 127.0504006
  },
  "서울특별시 은평구 진흥로15길 22-20 (불광동)": {
    "lat": 37.6106799,
    "lng": 126.9318075
  },
  "서울특별시 마포구 월드컵로42길 55 (상암동)": {
    "lat": 37.5792404,
    "lng": 126.8821136
  },
  "서울특별시 중랑구 신내로7나길 5 (신내동)": {
    "lat": 37.6017047,
    "lng": 127.0949852
  },
  "서울특별시 은평구 증산로11길 7-12 (증산동)": {
    "lat": 37.5865265,
    "lng": 126.9111306
  },
  "서울특별시 서초구 신반포로 127, 4층 (반포동, 반포2동열린문화센터)": {
    "lat": null,
    "lng": null
  },
  "서울특별시 강남구 헌릉로571길 48 (세곡동)": {
    "lat": 37.466128,
    "lng": 127.1016296
  },
  "서울특별시 송파구 송이로37길 11 (문정동)": {
    "lat": 37.4872475,
    "lng": 127.1345227
  },
  "서울특별시 강남구 봉은사로111길 18-3 (삼성동)": {
    "lat": 37.5169057,
    "lng": 127.0650001
  },
  "서울특별시 동대문구 전농동 146번지": {
    "lat": null,
    "lng": null
  },
  "서울특별시 마포구 마포대로 197-1 (아현동, 아현장로교회)": {
    "lat": 37.5541172,
    "lng": 126.9533384
  },
  "서울특별시 동대문구 왕산로17길 14 (용두동)": {
    "lat": null,
    "lng": null
  },
  "서울특별시 중랑구 면목로58길 41 (면목동)": {
    "lat": 37.5845092,
    "lng": 127.0898571
  },
  "서울특별시 종로구 난계로25길 54 (숭인동, 동대문성당)": {
    "lat": 37.5723893,
    "lng": 127.0208808
  },
  "서울특별시 광진구 능동로47길 15, 2층 (중곡동)": {
    "lat": null,
    "lng": null
  },
  "서울특별시 강남구 광평로 199 (수서동)": {
    "lat": 37.484169,
    "lng": 127.0948486
  },
  "서울특별시 강남구 강남대로44길 25 (도곡동)": {
    "lat": 37.4859817,
    "lng": 127.0348741
  },
  "서울특별시 성동구 무학봉길 69 (하왕십리동)": {
    "lat": 37.5595367,
    "lng": 127.0255042
  },
  "서울특별시 강남구 선릉로105길 5 (역삼동)": {
    "lat": 37.5083858,
    "lng": 127.0443044
  },
  "서울특별시 관악구 관악로5길 95 (봉천동, 1층)": {
    "lat": 37.4770743,
    "lng": 126.9512581
  },
  "서울특별시 동대문구 외대역동로5길 18 (휘경동, 동대문50플러스센터)": {
    "lat": 37.5927565,
    "lng": 127.0642298
  },
  "서울특별시 동작구 솔밭로 86 (사당동)": {
    "lat": 37.4840544,
    "lng": 126.967317
  },
  "서울특별시 종로구 대학로3길 14, 3층 (효제동, (북촌별관) 북촌로5가길 17-7)": {
    "lat": null,
    "lng": null
  },
  "서울특별시 동작구 매봉로 1 (상도1동)": {
    "lat": 37.5071514,
    "lng": 126.9514054
  },
  "서울특별시 동대문구 한천로58길 47 (이문동, 쌍용아파트)": {
    "lat": 37.6000381,
    "lng": 127.0683857
  },
  "서울특별시 강서구 마곡중앙5로 43 (마곡동)": {
    "lat": 37.5674456,
    "lng": 126.8179256
  },
  "서울특별시 서초구 방배중앙로 118, 2층 (방배동, 서초 시니어플라자)": {
    "lat": null,
    "lng": null
  },
  "서울특별시 강남구 논현로16길 11, 1층 (개포동)": {
    "lat": null,
    "lng": null
  },
  "서울특별시 은평구 진관2로 29-16 (진관동, 구파발성당)": {
    "lat": 37.6361233,
    "lng": 126.9198207
  },
  "서울특별시 중구 청구로3길 69 (신당동)": {
    "lat": 37.5577156,
    "lng": 127.014883
  },
  "서울특별시 금천구 한내로 69-15 (독산동, 주공13단지아파트)": {
    "lat": 37.4574523,
    "lng": 126.8866893
  },
  "서울특별시 금천구 독산로78길 20 (독산동)": {
    "lat": 37.4692975,
    "lng": 126.9034601
  },
  "서울특별시 금천구 두산로5길 19독산1동성당 (독산동)": {
    "lat": null,
    "lng": null
  },
  "서울특별시 금천구 금하로23다길 8 (시흥동)": {
    "lat": 37.452524,
    "lng": 126.9096271
  },
  "서울특별시 금천구 시흥대로90길 25신일교회 (독산동)": {
    "lat": null,
    "lng": null
  },
  "서울특별시 금천구 탑골로2길 56제일교회 (시흥동)": {
    "lat": null,
    "lng": null
  },
  "서울특별시 금천구 독산로38길 10시흥4동성당 (시흥동)": {
    "lat": null,
    "lng": null
  },
  "서울특별시 금천구 범안로17길 22 (독산동)": {
    "lat": 37.4676705,
    "lng": 126.894226
  },
  "서울특별시 금천구 시흥대로72길 13 (시흥동)": {
    "lat": 37.4571742,
    "lng": 126.9002909
  },
  "서울특별시 노원구 수락산로 214상계동 (상계동)": {
    "lat": null,
    "lng": null
  },
  "서울특별시 중랑구 용마산로94길 98 (면목동)": {
    "lat": 37.5874221,
    "lng": 127.1018221
  },
  "서울특별시 서대문구 통일로26길 12-5 (홍제동)": {
    "lat": 37.5833139,
    "lng": 126.9512835
  },
  "서울특별시 마포구 토정로31길 31 (용강동)": {
    "lat": 37.542347,
    "lng": 126.9430237
  },
  "서울특별시 양천구 목동중앙로3길 21 (목동)": {
    "lat": 37.5372984,
    "lng": 126.8683299
  },
  "서울특별시 동작구 남부순환로 2081 (사당동, 사당노인종합복지관)": {
    "lat": 37.4758946,
    "lng": 126.9725484
  },
  "서울특별시 동작구 노량진로 140 (노량진동, 메가스터디타워 2층)": {
    "lat": 37.5129262,
    "lng": 126.9417556
  },
  "서울특별시 영등포구 영등포동 645 번지 20 호": {
    "lat": null,
    "lng": null
  },
  "서울특별시 영등포구 여의도동 56번지 1호": {
    "lat": null,
    "lng": null
  },
  "서울특별시 강남구 도산대로53길 5 (신사동)": {
    "lat": 37.5244844,
    "lng": 127.0385937
  },
  "서울특별시 노원구 노원로30길 73 (상계동)": {
    "lat": 37.6561088,
    "lng": 127.0709696
  },
  "서울특별시 성동구 사근동길 37, 2층 (사근동)": {
    "lat": null,
    "lng": null
  },
  "서울특별시 양천구 지양로14길 17, 4층 (신월동, 신월7동주민센터)": {
    "lat": null,
    "lng": null
  },
  "서울특별시 은평구 역말로9길 대조노인복지관 대조 동": {
    "lat": null,
    "lng": null
  },
  "서울특별시 관악구 방천길 39 (신림동)": {
    "lat": 37.47313,
    "lng": 126.9327691
  },
  "서울특별시 중랑구 망우로65길 20 (신내동)": {
    "lat": 37.6012786,
    "lng": 127.0999587
  },
  "서울특별시 노원구 월계동  936번지": {
    "lat": null,
    "lng": null
  },
  "서울특별시 성북구 화랑로32길 88 (석관동)": {
    "lat": 37.606325,
    "lng": 127.0589072
  },
  "서울특별시 성북구 지봉로24길 26 (보문동5가)": {
    "lat": 37.5838729,
    "lng": 127.0193274
  },
  "서울특별시 서초구 염곡말길 느티나무쉼터": {
    "lat": null,
    "lng": null
  },
  "서울특별시 성동구 왕십리로5길 3, 6층 (성수동1가, 성수1가2동 공공복합청사)": {
    "lat": null,
    "lng": null
  },
  "서울특별시 성북구 삼선교로18길 41 (삼선동5가)": {
    "lat": 37.5873652,
    "lng": 127.0124764
  },
  "서울특별시 강남구 남부순환로378길 20, 1층-지하1층 (도곡동)": {
    "lat": null,
    "lng": null
  },
  "서울특별시 양천구 가로공원로60가길 16 (신월동)": {
    "lat": 37.5343963,
    "lng": 126.8262937
  },
  "서울특별시 금천구 한내로 69-15, 4층 (독산동, 독산1동 분소지역 복지관)": {
    "lat": null,
    "lng": null
  },
  "서울특별시 서초구 염곡말길 9 (염곡동)": {
    "lat": 37.4629925,
    "lng": 127.0555115
  },
  "서울특별시 서초구 남부순환로287길 17-4 (방배동)": {
    "lat": 37.4760745,
    "lng": 126.9875325
  },
  "서울특별시 도봉구 마들로 536, 5층 (창동)": {
    "lat": null,
    "lng": null
  },
  "서울특별시 성동구 용답동  183번지 3호": {
    "lat": null,
    "lng": null
  },
  "서울특별시 강북구 오현로9길 49 (미아동)": {
    "lat": 37.6187417,
    "lng": 127.0333801
  },
  "서울특별시 서초구 방배천로 48 (방배동)": {
    "lat": 37.4822631,
    "lng": 126.9826868
  }
}